{
  "game": {
    "names": ["World of Warcraft", "魔兽世界"],
    "classNames": ["GxWindowClass", "GxWindowClassD3d"]
  },
  "patch": {
    "MoP": {
      "customName": "",
      "delay": { "from": 50, "to": 150 },
      "castDelay": 1500,
      "sleepAfterHook": true,
      "afterHookDelay": { "from": 150, "to": 400 },
      "maxFishTime": 30000,
      "relZone": { "x": 0.3, "y": 0.01, "width": 0.4, "height": 0.416 },
      "checkingDelay": 50,
      "mouseMoveSpeed": 0.5,
      "mouseCurvatureStrength": 5,
      "luresDelay": 3000,
      "randomSleep": true,
      "randomSleepEvery": { "from": 1, "to": 3 },
      "randomSleepDelay": { "from": 1000, "to": 15000 },
      "reaction": true,
      "reactionDelay": { "from": 150, "to": 400 }
    },
    "Cataclysm": {
      "customName": "",
      "delay": { "from": 50, "to": 150 },
      "castDelay": 1500,
      "sleepAfterHook": true,
      "afterHookDelay": { "from": 150, "to": 400 },
      "maxFishTime": 30000,
      "relZone": { "x": 0.3, "y": 0.01, "width": 0.4, "height": 0.416 },
      "checkingDelay": 50,
      "mouseMoveSpeed": 0.5,
      "mouseCurvatureStrength": 5,
      "luresDelay": 3000,
      "randomSleep": true,
      "randomSleepEvery": { "from": 1, "to": 3 },
      "randomSleepDelay": { "from": 1000, "to": 15000 },
      "reaction": true,
      "reactionDelay": { "from": 150, "to": 400 }
    },
    "WoTLK": {
      "customName": "",
      "delay": { "from": 50, "to": 150 },
      "castDelay": 1500,
      "sleepAfterHook": true,
      "afterHookDelay": { "from": 150, "to": 400 },
      "maxFishTime": 30000,
      "relZone": { "x": 0.3, "y": 0.01, "width": 0.4, "height": 0.416 },
      "checkingDelay": 35,
      "mouseMoveSpeed": 0.5,
      "mouseCurvatureStrength": 5,
      "luresDelay": 3000,
      "randomSleep": true,
      "randomSleepEvery": { "from": 1, "to": 3 },
      "randomSleepDelay": { "from": 1000, "to": 15000 },
      "reaction": true,
      "reactionDelay": { "from": 150, "to": 400 }
    },
    "Retail&Classic": {
      "customName": "",
      "delay": { "from": 50, "to": 150 },
      "castDelay": 1500,
      "sleepAfterHook": true,
      "afterHookDelay": { "from": 150, "to": 400 },
      "maxFishTime": 30000,
      "relZone": { "x": 0.3, "y": 0.01, "width": 0.4, "height": 0.416 },
      "checkingDelay": 50,
      "mouseMoveSpeed": 0.5,
      "mouseCurvatureStrength": 5,
      "luresDelay": 3000,
      "randomSleep": true,
      "randomSleepEvery": { "from": 1, "to": 3 },
      "randomSleepDelay": { "from": 1000, "to": 15000 },
      "reaction": true,
      "reactionDelay": { "from": 150, "to": 400 }
    },
    "TBC": {
      "customName": "",
      "delay": { "from": 50, "to": 150 },
      "castDelay": 3000,
      "sleepAfterHook": true,
      "afterHookDelay": { "from": 150, "to": 400 },
      "maxFishTime": 30000,
      "relZone": { "x": 0.3, "y": 0.01, "width": 0.4, "height": 0.416 },
      "checkingDelay": 50,
      "mouseMoveSpeed": 0.5,
      "mouseCurvatureStrength": 5,
      "luresDelay": 3000,
      "randomSleep": true,
      "randomSleepEvery": { "from": 1, "to": 3 },
      "randomSleepDelay": { "from": 1000, "to": 15000 },
      "reaction": true,
      "reactionDelay": { "from": 150, "to": 400 }
    },
    "Vanilla": {
      "customName": "",
      "delay": { "from": 50, "to": 150 },
      "castDelay": 3000,
      "sleepAfterHook": true,
      "afterHookDelay": { "from": 150, "to": 400 },
      "maxFishTime": 30000,
      "relZone": { "x": 0.3, "y": 0.01, "width": 0.4, "height": 0.416 },
      "checkingDelay": 50,
      "mouseMoveSpeed": 0.5,
      "mouseCurvatureStrength": 5,
      "luresDelay": 3000,
      "randomSleep": true,
      "randomSleepEvery": { "from": 1, "to": 3 },
      "randomSleepDelay": { "from": 1000, "to": 15000 },
      "reaction": true,
      "reactionDelay": { "from": 150, "to": 400 }
    }
  }
}
